boomlify/__init__.py
boomlify/client.py
boomlify/exceptions.py
boomlify/models.py
boomlify-1.0.1.dist-info/licenses/LICENSE
boomlify-1.0.1.dist-info/METADATA
boomlify-1.0.1.dist-info/WHEEL
boomlify-1.0.1.dist-info/top_level.txt
boomlify-1.0.1.dist-info/RECORD
